setup.py
python_wikiware.egg-info/PKG-INFO
python_wikiware.egg-info/SOURCES.txt
python_wikiware.egg-info/dependency_links.txt
python_wikiware.egg-info/requires.txt
python_wikiware.egg-info/top_level.txt
wikiware/__init__.py
wikiware/defaults.py
wikiware/fetcher.py
wikiware/parser.py
wikiware/patterns.py
wikiware/test.py
wikiware/utils.py
wikiware/wiki.py