Metadata-Version: 1.1
Name: python-wikiware
Version: 0.0.1
Summary: A Python application that handles data extraction from Wikipedia
Home-page: https://github.com/un33k/python-wikiware
Author: Val Neekman
Author-email: info@neekware.com
License: BSD
Platform: UNKNOWN
Classifier: Development Status :: 3 - Alpha
Classifier: Intended Audience :: Developers
Classifier: License :: OSI Approved :: BSD License
Classifier: Operating System :: POSIX
Classifier: Programming Language :: Python
